{"nodes": [{"id": "m25_ble_sendcommand", "label": "_sendCommand", "file_type": "code", "source_file": "m25_ble.cpp", "source_location": null, "source_url": null, "captured_at": null, "author": null, "contributor": null}, {"id": "m25_ble_m25encrypt", "label": "_m25Encrypt (AES-128-CBC + CRC-16 + byte stuffing)", "file_type": "code", "source_file": "m25_ble.cpp", "source_location": null, "source_url": null, "captured_at": null, "author": null, "contributor": null}, {"id": "m25_ble_m25decrypt", "label": "_m25Decrypt", "file_type": "code", "source_file": "m25_ble.cpp", "source_location": null, "source_url": null, "captured_at": null, "author": null, "contributor": null}, {"id": "m25_ble_parseresponsedata", "label": "_parseResponseData", "file_type": "code", "source_file": "m25_ble.cpp", "source_location": null, "source_url": null, "captured_at": null, "author": null, "contributor": null}, {"id": "m25_ble_blerecordframe", "label": "_bleRecordFrame (traffic recorder)", "file_type": "code", "source_file": "m25_ble.cpp", "source_location": null, "source_url": null, "captured_at": null, "author": null, "contributor": null}, {"id": "m25_ble_bletxmutex", "label": "_bleTxMutex: serializes GATT writes to avoid isConnected() deadlock across Core0/Core1 tasks", "file_type": "rationale", "source_file": "m25_ble.cpp", "source_location": null, "source_url": null, "captured_at": null, "author": null, "contributor": null}, {"id": "m25_ble_blewheelmodename", "label": "bleWheelModeName", "file_type": "code", "source_file": "m25_ble.cpp", "source_location": null, "source_url": null, "captured_at": null, "author": null, "contributor": null}], "edges": [{"source": "m25_ble_sendcommand", "target": "logger_log", "relation": "references", "confidence": "EXTRACTED", "confidence_score": 1.0, "source_file": "m25_ble.cpp", "source_location": null, "weight": 1.0}, {"source": "m25_ble_wheelconnstate_t", "target": "device_config_wheel_mode", "relation": "shares_data_with", "confidence": "EXTRACTED", "confidence_score": 1.0, "source_file": "m25_ble.cpp", "source_location": null, "weight": 1.0}, {"source": "m25_ble_bletxmutex", "target": "supervisor_connecttaskbody", "relation": "conceptually_related_to", "confidence": "INFERRED", "confidence_score": 0.75, "source_file": "m25_ble.cpp", "source_location": null, "weight": 1.0}], "hyperedges": [{"id": "dual_core_ble_threading", "label": "Dual-core BLE threading pattern: Core 0 connect/motor tasks serialized via TX mutex, Core 1 loop", "nodes": ["supervisor_connecttaskbody", "m25_ble_blestartmotortask", "m25_ble_bletxmutex"], "relation": "participate_in", "confidence": "INFERRED", "confidence_score": 0.85, "source_file": "m25_ble.cpp"}]}